Joking/__init__.py
Joking-3.1.5.dist-info/LICENSE.txt
Joking-3.1.5.dist-info/METADATA
Joking-3.1.5.dist-info/WHEEL
Joking-3.1.5.dist-info/top_level.txt
Joking-3.1.5.dist-info/RECORD
