Metadata-Version: 2.1
Name: Joking
Version: 3.1.5
Summary: Joking is a python library for getting random/sudo-random jokes
Home-page: https://github.com/Iwertyuiop123653/Joker
Author: Hasty shrimp452
Author-email: hahacoolguystaco@gmail.com
License: MIT
Project-URL: Documentation, https://joking.readthedocs.io/en/latest/
Project-URL: Say Thanks!, https://saythanks.io/to/Iwertyuiop123653
Project-URL: Source, https://github.com/Iwertyuiop123653/Joker/
Project-URL: Tracker, https://github.com/Iwertyuiop123653/Joker/issues/
Keywords: Jokes
Platform: UNKNOWN
Classifier: Development Status :: 6 - Mature
Classifier: Intended Audience :: Developers
Classifier: Operating System :: OS Independent
Classifier: License :: OSI Approved :: MIT License
Classifier: Programming Language :: Python :: 3.10
License-File: LICENSE.txt
Requires-Dist: bs4
